[
    {
        "session_id": "496f78d5-6d26-436d-9baf-f08fd4151601",
        "id": "e7f850ce-7245-4f6a-95b7-d059eac29a2e",
        "email": "email@email.com",
        "username": "Default",
        "password": "password",
        "finance_account": {
            "income_sources": [
                {
                    "category": "merit_scholarship",
                    "date_unix": 1736554737029,
                    "amount_usd": 250
                },
                {
                    "category": "merit_scholarship",
                    "date_unix": 1737159537029,
                    "amount_usd": 800
                },
                {
                    "category": "merit_scholarship",
                    "date_unix": 1737764337029,
                    "amount_usd": 128.32
                },
                {
                    "category": "merit_scholarship",
                    "date_unix": 1738369137029,
                    "amount_usd": 1025.75
                },
                {
                    "category": "merit_scholarship",
                    "date_unix": 1738973937029,
                    "amount_usd": 450.1
                },
                {
                    "category": "merit_scholarship",
                    "date_unix": 1739578737029,
                    "amount_usd": 50
                },
                {
                    "category": "need_based_scholarship",
                    "date_unix": 1736554737233,
                    "amount_usd": 200
                },
                {
                    "category": "need_based_scholarship",
                    "date_unix": 1737159537233,
                    "amount_usd": 75
                },
                {
                    "category": "need_based_scholarship",
                    "date_unix": 1737764337233,
                    "amount_usd": 300
                },
                {
                    "category": "need_based_scholarship",
                    "date_unix": 1738369137233,
                    "amount_usd": 10
                },
                {
                    "category": "need_based_scholarship",
                    "date_unix": 1738973937233,
                    "amount_usd": 150
                },
                {
                    "category": "sports_scholarship",
                    "date_unix": 1736554737509,
                    "amount_usd": 1200
                },
                {
                    "category": "sports_scholarship",
                    "date_unix": 1737159537509,
                    "amount_usd": 500.5
                },
                {
                    "category": "sports_scholarship",
                    "date_unix": 1737764337509,
                    "amount_usd": 600.25
                },
                {
                    "category": "sports_scholarship",
                    "date_unix": 1738369137509,
                    "amount_usd": 700
                }
            ],
            "expenses": [
                {
                    "category": "transportation",
                    "date_unix": 1710451766458,
                    "amount_usd": 500
                },
                {
                    "category": "transportation",
                    "date_unix": 1732803700659,
                    "amount_usd": 102.93
                },
                {
                    "category": "transportation",
                    "date_unix": 1639478487463,
                    "amount_usd": 15.75
                },
                {
                    "category": "transportation",
                    "date_unix": 1843762056106,
                    "amount_usd": 60.3
                },
                {
                    "category": "transportation",
                    "date_unix": 1745484966251,
                    "amount_usd": 23.99
                },
                {
                    "category": "groceries",
                    "date_unix": 1811895014676,
                    "amount_usd": 150.6
                },
                {
                    "category": "groceries",
                    "date_unix": 1577421125543,
                    "amount_usd": 200.45
                },
                {
                    "category": "groceries",
                    "date_unix": 1821963910005,
                    "amount_usd": 78.99
                },
                {
                    "category": "groceries",
                    "date_unix": 1778599937821,
                    "amount_usd": 55
                },
                {
                    "category": "groceries",
                    "date_unix": 1879773843954,
                    "amount_usd": 89.1
                },
                {
                    "category": "entertainment",
                    "date_unix": 1576500980252,
                    "amount_usd": 50
                },
                {
                    "category": "entertainment",
                    "date_unix": 1690364773965,
                    "amount_usd": 120
                },
                {
                    "category": "entertainment",
                    "date_unix": 1809341488560,
                    "amount_usd": 90.5
                },
                {
                    "category": "entertainment",
                    "date_unix": 1586980858298,
                    "amount_usd": 35
                },
                {
                    "category": "entertainment",
                    "date_unix": 1725524607782,
                    "amount_usd": 20
                },
                {
                    "category": "transportation",
                    "date_unix": 1750000000000,
                    "amount_usd": 45
                },
                {
                    "category": "groceries",
                    "date_unix": 1750000000002,
                    "amount_usd": 100
                },
                {
                    "category": "entertainment",
                    "date_unix": 1750000000003,
                    "amount_usd": 75
                }
            ]
        }
    }
]